README.md
setup.py
django_urlman/__init__.py
django_urlman/urlman.py
django_urlman.egg-info/PKG-INFO
django_urlman.egg-info/SOURCES.txt
django_urlman.egg-info/dependency_links.txt
django_urlman.egg-info/top_level.txt