Metadata-Version: 2.1
Name: django-urlman
Version: 0.1.0
Summary: UNKNOWN
Home-page: https://github.com/randydu/django-urlman.git
Author: randydu
Author-email: randydu@gmail.com
License: MIT
Download-URL: https://github.com/randydu/django-urlman/archive/v0.1.0.tar.gz
Keywords: django,url,route
Platform: UNKNOWN
Classifier: Development Status :: 2 - Pre-Alpha
Classifier: Intended Audience :: Developers
Classifier: Operating System :: OS Independent
Classifier: Topic :: Software Development :: Libraries
Classifier: Topic :: Software Development :: Libraries :: Python Modules
Classifier: License :: OSI Approved :: MIT License
Classifier: Programming Language :: Python :: 3
